{
	"nodes": [
		{
			"id": "startNode-17ef7925-0583-4fff-9161-ab4293b5631d",
			"type": "startNode",
			"sourcePosition": "right",
			"position": {
				"x": 30,
				"y": 30
			},
			"deletable": false,
			"data": {
				"id": "startNode-17ef7925-0583-4fff-9161-ab4293b5631d",
				"type": "startNode",
				"position": {
					"x": 30,
					"y": 40
				},
				"agamaData": {
					"isTopLevelFlow": true,
					"basepath": "",
					"configParams": "{}",
					"nodeIcon": "material-symbols:line-start-square",
					"timeout": "900",
					"inputs": "PhonenumberUpdateService username phone",
					"configs": "",
					"flowname": "org.gluu.agama.change.smsotp",
					"displayName": "org.gluu.agama.change.smsotp",
					"creationDate": "09/10/2025",
					"hasComment": true,
					"comment": ""
				}
			},
			"measured": {
				"width": 170,
				"height": 122
			},
			"selected": false
		},
		{
			"id": "logNode-49b8e2aa-a9dd-4649-a440-dec7cfacb9d4",
			"type": "logNode",
			"position": {
				"x": 280,
				"y": 30
			},
			"data": {
				"id": "logNode-49b8e2aa-a9dd-4649-a440-dec7cfacb9d4",
				"type": "logNode",
				"position": {
					"x": 280,
					"y": 30
				},
				"previousNodeId": "startNode-17ef7925-0583-4fff-9161-ab4293b5631d",
				"agamaData": {
					"logMessage": "\"Information received from the caller: \" username phone",
					"logLevel": "info",
					"nodeIcon": "octicon:log-16",
					"nodeColor": "",
					"titleColor": "",
					"descColor": "",
					"displayName": "Log flow imputs",
					"hasComment": true,
					"comment": "Log flow imputs provided by the flow caller."
				}
			},
			"measured": {
				"width": 168,
				"height": 120
			},
			"selected": false
		},
		{
			"id": "assignmentNode-552116a5-357d-4289-a55e-7d7635dd7a83",
			"type": "assignmentNode",
			"position": {
				"x": 530,
				"y": 30
			},
			"data": {
				"id": "assignmentNode-552116a5-357d-4289-a55e-7d7635dd7a83",
				"type": "assignmentNode",
				"position": {
					"x": 530,
					"y": 30
				},
				"previousNodeId": "logNode-49b8e2aa-a9dd-4649-a440-dec7cfacb9d4",
				"agamaData": {
					"assignments": [
						{
							"variableTypeCheck": true,
							"assignmentExpression": "{}",
							"assignedVariableName": "otpUiFeedback"
						},
						{
							"variableTypeCheck": true,
							"assignmentExpression": "0",
							"assignedVariableName": "resendCount"
						},
						{
							"variableTypeCheck": true,
							"assignmentExpression": "0",
							"assignedVariableName": "validationAttempts"
						}
					],
					"nodeIcon": "material-symbols:equal",
					"nodeColor": "",
					"titleColor": "",
					"descColor": "",
					"displayName": "Declare feedback Variable",
					"hasComment": true,
					"comment": "Declare feedback Variable"
				}
			},
			"measured": {
				"width": 170,
				"height": 122
			},
			"selected": false
		},
		{
			"id": "repeatNode-1837b2b3-fb17-4d9d-9ddb-565e2ab15a55",
			"type": "repeatNode",
			"position": {
				"x": 780,
				"y": 30
			},
			"data": {
				"id": "repeatNode-1837b2b3-fb17-4d9d-9ddb-565e2ab15a55",
				"type": "repeatNode",
				"position": {
					"x": 780,
					"y": 30
				},
				"previousNodeId": "assignmentNode-552116a5-357d-4289-a55e-7d7635dd7a83",
				"agamaData": {
					"nodeIcon": "material-symbols:event-repeat-outline-rounded",
					"maxIteration": "20",
					"maxIterationVariableName": "maxSMS",
					"nodeColor": "",
					"titleColor": "",
					"descColor": "",
					"displayName": "Valid sms OTP check",
					"hasComment": true,
					"comment": ""
				}
			},
			"measured": {
				"width": 170,
				"height": 122
			},
			"selected": false
		},
		{
			"id": "logNode-ca599358-dab0-44bb-a86a-85b06fd8ea39",
			"type": "logNode",
			"position": {
				"x": 1030,
				"y": 30
			},
			"data": {
				"id": "logNode-ca599358-dab0-44bb-a86a-85b06fd8ea39",
				"type": "logNode",
				"position": {
					"x": 1030,
					"y": 30
				},
				"previousNodeId": "repeatNode-1837b2b3-fb17-4d9d-9ddb-565e2ab15a55",
				"branching": "continue",
				"agamaData": {
					"logMessage": "\"OTP verification loop completed\"",
					"logLevel": "info",
					"nodeIcon": "octicon:log-16",
					"nodeColor": "",
					"titleColor": "",
					"descColor": "",
					"displayName": "",
					"hasComment": true,
					"comment": "\"OTP verification loop completed\""
				}
			},
			"measured": {
				"width": 170,
				"height": 122
			},
			"selected": false
		},
		{
			"id": "assignmentNode-71530d3e-429a-41c7-8dc5-183d9e016a11",
			"type": "assignmentNode",
			"position": {
				"x": 1280,
				"y": 30
			},
			"data": {
				"id": "assignmentNode-71530d3e-429a-41c7-8dc5-183d9e016a11",
				"type": "assignmentNode",
				"position": {
					"x": 1280,
					"y": 30
				},
				"previousNodeId": "logNode-ca599358-dab0-44bb-a86a-85b06fd8ea39",
				"agamaData": {
					"assignments": [
						{
							"variableTypeCheck": true,
							"assignmentExpression": "{ success: false, error: \"UnexpectedLoopCompletion\" }",
							"assignedVariableName": "it_loopmax"
						}
					],
					"nodeIcon": "material-symbols:equal",
					"nodeColor": "",
					"titleColor": "",
					"descColor": "",
					"displayName": "Max SMS Otp tried",
					"hasComment": true,
					"comment": ""
				}
			},
			"measured": {
				"width": 170,
				"height": 122
			},
			"selected": false
		},
		{
			"id": "finishNode-1d86276d-8535-467c-817f-3073f4257e8b",
			"type": "finishNode",
			"position": {
				"x": 1530,
				"y": 30
			},
			"data": {
				"id": "finishNode-1d86276d-8535-467c-817f-3073f4257e8b",
				"type": "finishNode",
				"position": {
					"x": 1530,
					"y": 30
				},
				"previousNodeId": "assignmentNode-71530d3e-429a-41c7-8dc5-183d9e016a11",
				"agamaData": {
					"nodeColor": "",
					"titleColor": "",
					"descColor": "",
					"displayName": "End unexpected completion",
					"hasComment": true,
					"comment": "SMS OTP error",
					"flowfilename": "",
					"returnVariable": "it_loopmax",
					"nodeIcon": "material-symbols:line-end-square-rounded",
					"finishMode": "withVariable"
				}
			},
			"measured": {
				"width": 170,
				"height": 122
			},
			"selected": false
		},
		{
			"id": "rrfNode-e648f293-0be3-49fc-b069-38f1e1ccf4fd",
			"type": "rrfNode",
			"position": {
				"x": 1093.3538203292146,
				"y": 382.51800016909294
			},
			"data": {
				"id": "rrfNode-e648f293-0be3-49fc-b069-38f1e1ccf4fd",
				"type": "rrfNode",
				"position": {
					"x": 1030,
					"y": 280
				},
				"previousNodeId": "repeatNode-1837b2b3-fb17-4d9d-9ddb-565e2ab15a55",
				"branching": "repeat",
				"agamaData": {
					"assignments": [],
					"nodeIcon": "ph:globe-simple",
					"templatePath": "smsOtp.ftlh",
					"asssignedVariableName": "otpCreds",
					"nodeColor": "",
					"titleColor": "",
					"descColor": "",
					"displayName": "RRF",
					"hasComment": true,
					"comment": " Show UI to collect OTP code from user.",
					"arguments": "otpUiFeedback"
				}
			},
			"measured": {
				"width": 170,
				"height": 122
			},
			"selected": false,
			"dragging": false
		},
		{
			"id": "whenNode-565629fd-462f-41ea-9569-63364bb79245",
			"type": "whenNode",
			"position": {
				"x": 1630.200883265409,
				"y": 400.5259889924593
			},
			"data": {
				"id": "whenNode-565629fd-462f-41ea-9569-63364bb79245",
				"type": "whenNode",
				"position": {
					"x": 1575.8002325009254,
					"y": 226.70927557423113
				},
				"previousNodeId": "rrfNode-e648f293-0be3-49fc-b069-38f1e1ccf4fd",
				"branching": "otherwise",
				"agamaData": {
					"variableField": "",
					"valueField": "",
					"conditionInputField": "",
					"conditions": [
						{
							"variable": "otpCreds.hasRequestedNewCode",
							"operator": "is",
							"dataValue": "\"yes\"",
							"combinator": "none"
						}
					],
					"nodeIcon": "ph:swap",
					"nodeColor": "",
					"titleColor": "",
					"descColor": "",
					"displayName": "",
					"hasComment": true,
					"comment": ""
				}
			},
			"measured": {
				"width": 110,
				"height": 59
			},
			"selected": false,
			"dragging": false
		},
		{
			"id": "logNode-df73659a-2b4d-49ae-b310-11f427795928",
			"type": "logNode",
			"position": {
				"x": 1880.200883265409,
				"y": 600.5259889924594
			},
			"data": {
				"id": "logNode-df73659a-2b4d-49ae-b310-11f427795928",
				"type": "logNode",
				"position": {
					"x": 1880.200883265409,
					"y": 600.5259889924594
				},
				"previousNodeId": "whenNode-565629fd-462f-41ea-9569-63364bb79245",
				"branching": "success",
				"agamaData": {
					"logMessage": "\"User has requested a new code.\"",
					"logLevel": "info",
					"nodeIcon": "octicon:log-16",
					"nodeColor": "",
					"titleColor": "",
					"descColor": "",
					"displayName": "Log new code request",
					"hasComment": true,
					"comment": "Log new code request"
				}
			},
			"measured": {
				"width": 168,
				"height": 120
			},
			"selected": false
		},
		{
			"id": "logNode-ebb1a63c-79c3-429a-8584-5792c4e85b0d",
			"type": "logNode",
			"position": {
				"x": 1880.200883265409,
				"y": 150.5259889924593
			},
			"data": {
				"id": "logNode-ebb1a63c-79c3-429a-8584-5792c4e85b0d",
				"type": "logNode",
				"position": {
					"x": 1880.200883265409,
					"y": 150.5259889924593
				},
				"previousNodeId": "whenNode-565629fd-462f-41ea-9569-63364bb79245",
				"branching": "otherwise",
				"agamaData": {
					"logMessage": "\"Information provided by the user is : \" otpCreds.code",
					"logLevel": "info",
					"nodeIcon": "octicon:log-16",
					"nodeColor": "",
					"titleColor": "",
					"descColor": "",
					"displayName": "LOG",
					"hasComment": true,
					"comment": " Add log entry with collected code in log file."
				}
			},
			"measured": {
				"width": 168,
				"height": 120
			},
			"selected": false
		},
		{
			"id": "callNode-7d1be4ad-4c7b-4560-b5c6-00888d8ec0fb",
			"type": "callNode",
			"position": {
				"x": 2130.200883265409,
				"y": 150.5259889924593
			},
			"data": {
				"id": "callNode-7d1be4ad-4c7b-4560-b5c6-00888d8ec0fb",
				"type": "callNode",
				"position": {
					"x": 2130.200883265409,
					"y": 150.5259889924593
				},
				"previousNodeId": "logNode-ebb1a63c-79c3-429a-8584-5792c4e85b0d",
				"agamaData": {
					"javaClassName": "org.gluu.agama.login.CounterHelper",
					"javaMethodName": "increment",
					"javaVariableName": "",
					"exceptionVariableField": "",
					"callType": "Call static method",
					"arguments": [
						"validationAttempts"
					],
					"nodeIcon": "material-symbols:code",
					"nodeColor": "",
					"titleColor": "",
					"descColor": "",
					"displayName": "validationAttempts",
					"hasComment": true,
					"comment": "validationAttempts",
					"asssignedVariableName": "validationAttempts"
				}
			},
			"measured": {
				"width": 170,
				"height": 122
			},
			"selected": false
		},
		{
			"id": "logNode-50f1a038-394b-480f-8f50-84cf776b199e",
			"type": "logNode",
			"position": {
				"x": 2380.200883265409,
				"y": 150.5259889924593
			},
			"data": {
				"id": "logNode-50f1a038-394b-480f-8f50-84cf776b199e",
				"type": "logNode",
				"position": {
					"x": 2380.200883265409,
					"y": 150.5259889924593
				},
				"previousNodeId": "callNode-7d1be4ad-4c7b-4560-b5c6-00888d8ec0fb",
				"agamaData": {
					"logMessage": "\"Validation attempt number: \" validationAttempts",
					"logLevel": "info",
					"nodeIcon": "octicon:log-16",
					"nodeColor": "",
					"titleColor": "",
					"descColor": "",
					"displayName": "Log validation attempt",
					"hasComment": true,
					"comment": "Add log entry withvalidation result in log file."
				}
			},
			"measured": {
				"width": 168,
				"height": 120
			},
			"selected": false
		},
		{
			"id": "whenNode-9d8420e5-ffa7-4dd2-8f27-3540457b3079",
			"type": "whenNode",
			"position": {
				"x": 2130.200883265409,
				"y": 658.5259889924594
			},
			"data": {
				"id": "whenNode-9d8420e5-ffa7-4dd2-8f27-3540457b3079",
				"type": "whenNode",
				"position": {
					"x": 2130.200883265409,
					"y": 658.5259889924594
				},
				"previousNodeId": "logNode-df73659a-2b4d-49ae-b310-11f427795928",
				"agamaData": {
					"variableField": "",
					"valueField": "",
					"conditionInputField": "",
					"conditions": [],
					"nodeIcon": "ph:swap",
					"nodeColor": "",
					"titleColor": "",
					"descColor": "",
					"displayName": "",
					"hasComment": true,
					"comment": ""
				}
			},
			"measured": {
				"width": 110,
				"height": 59
			}
		},
		{
			"id": "whenNode-f9ebdc7e-d721-4918-824f-b38b8038e305",
			"type": "whenNode",
			"position": {
				"x": 2630.200883265409,
				"y": 208.5259889924593
			},
			"data": {
				"id": "whenNode-f9ebdc7e-d721-4918-824f-b38b8038e305",
				"type": "whenNode",
				"position": {
					"x": 2630.200883265409,
					"y": 208.5259889924593
				},
				"previousNodeId": "logNode-50f1a038-394b-480f-8f50-84cf776b199e",
				"agamaData": {
					"variableField": "",
					"valueField": "",
					"conditionInputField": "",
					"conditions": [
						{
							"variable": "validationAttempts",
							"operator": "is",
							"dataValue": "4",
							"combinator": "none"
						}
					],
					"nodeIcon": "ph:swap",
					"nodeColor": "",
					"titleColor": "",
					"descColor": "",
					"displayName": "",
					"hasComment": true,
					"comment": "Check validation"
				}
			},
			"measured": {
				"width": 110,
				"height": 59
			},
			"selected": false
		},
		{
			"id": "callNode-f1dd0934-98df-44c6-8be3-5004c1f0e2d3",
			"type": "callNode",
			"position": {
				"x": 2880.200883265409,
				"y": -41.474011007540696
			},
			"data": {
				"id": "callNode-f1dd0934-98df-44c6-8be3-5004c1f0e2d3",
				"type": "callNode",
				"position": {
					"x": 2880.200883265409,
					"y": -41.474011007540696
				},
				"previousNodeId": "whenNode-f9ebdc7e-d721-4918-824f-b38b8038e305",
				"branching": "otherwise",
				"agamaData": {
					"javaClassName": "",
					"javaMethodName": "validateOTPCode",
					"javaVariableName": "validationAttempts",
					"exceptionVariableField": "",
					"callType": "Call method on instance",
					"arguments": [
						"phone",
						"otpCreds.code"
					],
					"nodeIcon": "material-symbols:code",
					"nodeColor": "",
					"titleColor": "",
					"descColor": "",
					"displayName": "",
					"hasComment": true,
					"comment": " Validate the OTP code provided by the user.",
					"asssignedVariableName": "otpValidationResult"
				}
			},
			"measured": {
				"width": 170,
				"height": 122
			},
			"selected": false
		},
		{
			"id": "logNode-1c83b6bc-3cda-4381-941a-5f609d01a12b",
			"type": "logNode",
			"position": {
				"x": 3130.200883265409,
				"y": -41.474011007540696
			},
			"data": {
				"id": "logNode-1c83b6bc-3cda-4381-941a-5f609d01a12b",
				"type": "logNode",
				"position": {
					"x": 3130.200883265409,
					"y": -41.474011007540696
				},
				"previousNodeId": "callNode-f1dd0934-98df-44c6-8be3-5004c1f0e2d3",
				"agamaData": {
					"logMessage": "\"OTP validation result is:\" otpValidationResult",
					"logLevel": "info",
					"nodeIcon": "octicon:log-16",
					"nodeColor": "",
					"titleColor": "",
					"descColor": "",
					"displayName": "Log validation result",
					"hasComment": true,
					"comment": "Add log entry withvalidation result in log file."
				}
			},
			"measured": {
				"width": 170,
				"height": 122
			},
			"selected": false
		},
		{
			"id": "whenNode-5596e065-1f33-42db-a454-cc1f89e59ea2",
			"type": "whenNode",
			"position": {
				"x": 3380.200883265409,
				"y": 16.525988992459304
			},
			"data": {
				"id": "whenNode-5596e065-1f33-42db-a454-cc1f89e59ea2",
				"type": "whenNode",
				"position": {
					"x": 3380.200883265409,
					"y": 16.525988992459304
				},
				"previousNodeId": "logNode-1c83b6bc-3cda-4381-941a-5f609d01a12b",
				"agamaData": {
					"variableField": "",
					"valueField": "",
					"conditionInputField": "",
					"conditions": [
						{
							"variable": "otpValidationResult",
							"operator": "is",
							"dataValue": "true",
							"combinator": "none"
						}
					],
					"nodeIcon": "ph:swap",
					"nodeColor": "",
					"titleColor": "",
					"descColor": "",
					"displayName": "",
					"hasComment": true,
					"comment": "If otp validation was successful"
				}
			},
			"measured": {
				"width": 110,
				"height": 59
			},
			"selected": false
		},
		{
			"id": "logNode-40a9057c-7f7b-4ec3-b841-a23ae6394b5f",
			"type": "logNode",
			"position": {
				"x": 3630.200883265409,
				"y": -233.4740110075407
			},
			"data": {
				"id": "logNode-40a9057c-7f7b-4ec3-b841-a23ae6394b5f",
				"type": "logNode",
				"position": {
					"x": 3630.200883265409,
					"y": -233.4740110075407
				},
				"previousNodeId": "whenNode-5596e065-1f33-42db-a454-cc1f89e59ea2",
				"branching": "otherwise",
				"agamaData": {
					"logMessage": "\"Invalid code provided \"",
					"logLevel": "info",
					"nodeIcon": "octicon:log-16",
					"nodeColor": "",
					"titleColor": "",
					"descColor": "",
					"displayName": "Log invalid code",
					"hasComment": true,
					"comment": "The maximum number of attempt has been reached."
				}
			},
			"measured": {
				"width": 170,
				"height": 122
			},
			"selected": false
		},
		{
			"id": "assignmentNode-93e25ccb-9795-45db-b492-11eeb627c357",
			"type": "assignmentNode",
			"position": {
				"x": 3880.200883265409,
				"y": -233.4740110075407
			},
			"data": {
				"id": "assignmentNode-93e25ccb-9795-45db-b492-11eeb627c357",
				"type": "assignmentNode",
				"position": {
					"x": 3880.200883265409,
					"y": -233.4740110075407
				},
				"previousNodeId": "logNode-40a9057c-7f7b-4ec3-b841-a23ae6394b5f",
				"agamaData": {
					"assignments": [
						{
							"variableTypeCheck": true,
							"assignmentExpression": "\"Invalid code provided.\"",
							"assignedVariableName": "otpUiFeedback.errorMessage"
						},
						{
							"variableTypeCheck": true,
							"assignmentExpression": "\"\"",
							"assignedVariableName": "otpUiFeedback.infoMessage"
						}
					],
					"nodeIcon": "material-symbols:equal",
					"nodeColor": "",
					"titleColor": "",
					"descColor": "",
					"displayName": "Provide feedback",
					"hasComment": true,
					"comment": "Provide feedback to user."
				}
			},
			"measured": {
				"width": 170,
				"height": 122
			},
			"selected": true
		},
		{
			"id": "logNode-3a60855c-7abf-45a9-a26a-34db60545fd7",
			"type": "logNode",
			"position": {
				"x": 3630.200883265409,
				"y": 216.5259889924593
			},
			"data": {
				"id": "logNode-3a60855c-7abf-45a9-a26a-34db60545fd7",
				"type": "logNode",
				"position": {
					"x": 3630.200883265409,
					"y": 216.5259889924593
				},
				"previousNodeId": "whenNode-5596e065-1f33-42db-a454-cc1f89e59ea2",
				"branching": "success",
				"agamaData": {
					"logMessage": "",
					"logLevel": "",
					"nodeIcon": "octicon:log-16",
					"nodeColor": "",
					"titleColor": "",
					"descColor": "",
					"displayName": "",
					"hasComment": true,
					"comment": ""
				}
			},
			"measured": {
				"width": 170,
				"height": 122
			}
		},
		{
			"id": "finishNode-40609603-e9c5-4c5c-a9c2-f8e88c2922d0",
			"type": "finishNode",
			"position": {
				"x": 3880.200883265409,
				"y": 216.5259889924593
			},
			"data": {
				"id": "finishNode-40609603-e9c5-4c5c-a9c2-f8e88c2922d0",
				"type": "finishNode",
				"position": {
					"x": 3880.200883265409,
					"y": 216.5259889924593
				},
				"previousNodeId": "logNode-3a60855c-7abf-45a9-a26a-34db60545fd7",
				"agamaData": {
					"nodeColor": "",
					"titleColor": "",
					"descColor": "",
					"displayName": "",
					"hasComment": true,
					"comment": "",
					"flowfilename": "",
					"returnVariable": "",
					"nodeIcon": "material-symbols:line-end-square-rounded"
				}
			},
			"measured": {
				"width": 170,
				"height": 122
			}
		},
		{
			"id": "logNode-f2e8f64e-824e-40a0-acce-a5d19efa7cb3",
			"type": "logNode",
			"position": {
				"x": 2880.200883265409,
				"y": 408.5259889924593
			},
			"data": {
				"id": "logNode-f2e8f64e-824e-40a0-acce-a5d19efa7cb3",
				"type": "logNode",
				"position": {
					"x": 2880.200883265409,
					"y": 408.5259889924593
				},
				"previousNodeId": "whenNode-f9ebdc7e-d721-4918-824f-b38b8038e305",
				"branching": "success",
				"agamaData": {
					"logMessage": "",
					"logLevel": "",
					"nodeIcon": "octicon:log-16",
					"nodeColor": "",
					"titleColor": "",
					"descColor": "",
					"displayName": "",
					"hasComment": true,
					"comment": ""
				}
			},
			"measured": {
				"width": 168,
				"height": 120
			}
		},
		{
			"id": "assignmentNode-50a70c3d-93ee-4d21-a021-2d41e201b932",
			"type": "assignmentNode",
			"position": {
				"x": 3130.200883265409,
				"y": 408.5259889924593
			},
			"data": {
				"id": "assignmentNode-50a70c3d-93ee-4d21-a021-2d41e201b932",
				"type": "assignmentNode",
				"position": {
					"x": 3130.200883265409,
					"y": 408.5259889924593
				},
				"previousNodeId": "logNode-f2e8f64e-824e-40a0-acce-a5d19efa7cb3",
				"agamaData": {
					"assignments": [],
					"nodeIcon": "material-symbols:equal",
					"nodeColor": "",
					"titleColor": "",
					"descColor": "",
					"displayName": "",
					"hasComment": true,
					"comment": ""
				}
			},
			"measured": {
				"width": 170,
				"height": 122
			}
		},
		{
			"id": "iterateOverNode-0520ffc9-fed3-4107-af27-830de213457a",
			"type": "iterateOverNode",
			"position": {
				"x": 3380.200883265409,
				"y": 408.5259889924593
			},
			"data": {
				"id": "iterateOverNode-0520ffc9-fed3-4107-af27-830de213457a",
				"type": "iterateOverNode",
				"position": {
					"x": 3380.200883265409,
					"y": 408.5259889924593
				},
				"previousNodeId": "assignmentNode-50a70c3d-93ee-4d21-a021-2d41e201b932",
				"agamaData": {
					"iterateOn": [],
					"iterateAs": "",
					"iterateResult": "",
					"nodeColor": "",
					"titleColor": "",
					"descColor": "",
					"displayName": "",
					"hasComment": true,
					"comment": "",
					"nodeIcon": "ph:swap"
				}
			},
			"measured": {
				"width": 170,
				"height": 122
			}
		}
	],
	"edges": [
		{
			"id": "startNode-17ef7925-0583-4fff-9161-ab4293b5631d-logNode-49b8e2aa-a9dd-4649-a440-dec7cfacb9d4",
			"type": "default",
			"source": "startNode-17ef7925-0583-4fff-9161-ab4293b5631d",
			"target": "logNode-49b8e2aa-a9dd-4649-a440-dec7cfacb9d4",
			"labelBgPadding": [
				8,
				4
			],
			"labelBgBorderRadius": 4,
			"label": "",
			"labelBgStyle": {
				"fill": "#009688",
				"color": "#ffffff",
				"fillOpacity": 0.7
			},
			"labelShowBg": true,
			"sourceHandle": "source_startNode-17ef7925-0583-4fff-9161-ab4293b5631d"
		},
		{
			"id": "logNode-49b8e2aa-a9dd-4649-a440-dec7cfacb9d4-assignmentNode-552116a5-357d-4289-a55e-7d7635dd7a83",
			"type": "default",
			"source": "logNode-49b8e2aa-a9dd-4649-a440-dec7cfacb9d4",
			"target": "assignmentNode-552116a5-357d-4289-a55e-7d7635dd7a83",
			"labelBgPadding": [
				8,
				4
			],
			"labelBgBorderRadius": 4,
			"label": "",
			"labelBgStyle": {
				"fill": "#009688",
				"color": "#ffffff",
				"fillOpacity": 0.7
			},
			"labelShowBg": true,
			"sourceHandle": "source_logNode-49b8e2aa-a9dd-4649-a440-dec7cfacb9d4"
		},
		{
			"id": "assignmentNode-552116a5-357d-4289-a55e-7d7635dd7a83-repeatNode-1837b2b3-fb17-4d9d-9ddb-565e2ab15a55",
			"type": "default",
			"source": "assignmentNode-552116a5-357d-4289-a55e-7d7635dd7a83",
			"target": "repeatNode-1837b2b3-fb17-4d9d-9ddb-565e2ab15a55",
			"labelBgPadding": [
				8,
				4
			],
			"labelBgBorderRadius": 4,
			"label": "",
			"labelBgStyle": {
				"fill": "#009688",
				"color": "#ffffff",
				"fillOpacity": 0.7
			},
			"labelShowBg": true,
			"sourceHandle": "source_assignmentNode-552116a5-357d-4289-a55e-7d7635dd7a83"
		},
		{
			"id": "repeatNode-1837b2b3-fb17-4d9d-9ddb-565e2ab15a55-logNode-ca599358-dab0-44bb-a86a-85b06fd8ea39",
			"type": "default",
			"source": "repeatNode-1837b2b3-fb17-4d9d-9ddb-565e2ab15a55",
			"target": "logNode-ca599358-dab0-44bb-a86a-85b06fd8ea39",
			"labelBgPadding": [
				8,
				4
			],
			"labelBgBorderRadius": 4,
			"label": "continue",
			"labelBgStyle": {
				"fill": "#009688",
				"color": "#ffffff",
				"fillOpacity": 0.7
			},
			"labelShowBg": true,
			"sourceHandle": "source_repeatNode-1837b2b3-fb17-4d9d-9ddb-565e2ab15a55_continue"
		},
		{
			"id": "logNode-ca599358-dab0-44bb-a86a-85b06fd8ea39-assignmentNode-71530d3e-429a-41c7-8dc5-183d9e016a11",
			"type": "default",
			"source": "logNode-ca599358-dab0-44bb-a86a-85b06fd8ea39",
			"target": "assignmentNode-71530d3e-429a-41c7-8dc5-183d9e016a11",
			"labelBgPadding": [
				8,
				4
			],
			"labelBgBorderRadius": 4,
			"label": "",
			"labelBgStyle": {
				"fill": "#009688",
				"color": "#ffffff",
				"fillOpacity": 0.7
			},
			"labelShowBg": true,
			"sourceHandle": "source_logNode-ca599358-dab0-44bb-a86a-85b06fd8ea39"
		},
		{
			"id": "assignmentNode-71530d3e-429a-41c7-8dc5-183d9e016a11-finishNode-1d86276d-8535-467c-817f-3073f4257e8b",
			"type": "default",
			"source": "assignmentNode-71530d3e-429a-41c7-8dc5-183d9e016a11",
			"target": "finishNode-1d86276d-8535-467c-817f-3073f4257e8b",
			"labelBgPadding": [
				8,
				4
			],
			"labelBgBorderRadius": 4,
			"label": "",
			"labelBgStyle": {
				"fill": "#009688",
				"color": "#ffffff",
				"fillOpacity": 0.7
			},
			"labelShowBg": true,
			"sourceHandle": "source_assignmentNode-71530d3e-429a-41c7-8dc5-183d9e016a11"
		},
		{
			"id": "repeatNode-1837b2b3-fb17-4d9d-9ddb-565e2ab15a55-rrfNode-e648f293-0be3-49fc-b069-38f1e1ccf4fd",
			"type": "default",
			"source": "repeatNode-1837b2b3-fb17-4d9d-9ddb-565e2ab15a55",
			"target": "rrfNode-e648f293-0be3-49fc-b069-38f1e1ccf4fd",
			"labelBgPadding": [
				8,
				4
			],
			"labelBgBorderRadius": 4,
			"label": "repeat",
			"labelBgStyle": {
				"fill": "#009688",
				"color": "#ffffff",
				"fillOpacity": 0.7
			},
			"labelShowBg": true,
			"sourceHandle": "source_repeatNode-1837b2b3-fb17-4d9d-9ddb-565e2ab15a55_repeat"
		},
		{
			"id": "whenNode-565629fd-462f-41ea-9569-63364bb79245-logNode-df73659a-2b4d-49ae-b310-11f427795928",
			"type": "default",
			"source": "whenNode-565629fd-462f-41ea-9569-63364bb79245",
			"target": "logNode-df73659a-2b4d-49ae-b310-11f427795928",
			"labelBgPadding": [
				8,
				4
			],
			"labelBgBorderRadius": 4,
			"label": "Condition met",
			"labelBgStyle": {
				"fill": "#009688",
				"color": "#ffffff",
				"fillOpacity": 0.7
			},
			"labelShowBg": true,
			"sourceHandle": "source_whenNode-565629fd-462f-41ea-9569-63364bb79245_success"
		},
		{
			"id": "whenNode-565629fd-462f-41ea-9569-63364bb79245-logNode-ebb1a63c-79c3-429a-8584-5792c4e85b0d",
			"type": "default",
			"source": "whenNode-565629fd-462f-41ea-9569-63364bb79245",
			"target": "logNode-ebb1a63c-79c3-429a-8584-5792c4e85b0d",
			"labelBgPadding": [
				8,
				4
			],
			"labelBgBorderRadius": 4,
			"label": "otherwise",
			"labelBgStyle": {
				"fill": "#009688",
				"color": "#ffffff",
				"fillOpacity": 0.7
			},
			"labelShowBg": true,
			"sourceHandle": "source_whenNode-565629fd-462f-41ea-9569-63364bb79245_otherwise"
		},
		{
			"id": "logNode-ebb1a63c-79c3-429a-8584-5792c4e85b0d-callNode-7d1be4ad-4c7b-4560-b5c6-00888d8ec0fb",
			"type": "default",
			"source": "logNode-ebb1a63c-79c3-429a-8584-5792c4e85b0d",
			"target": "callNode-7d1be4ad-4c7b-4560-b5c6-00888d8ec0fb",
			"labelBgPadding": [
				8,
				4
			],
			"labelBgBorderRadius": 4,
			"label": "",
			"labelBgStyle": {
				"fill": "#009688",
				"color": "#ffffff",
				"fillOpacity": 0.7
			},
			"labelShowBg": true,
			"sourceHandle": "source_logNode-ebb1a63c-79c3-429a-8584-5792c4e85b0d"
		},
		{
			"id": "callNode-7d1be4ad-4c7b-4560-b5c6-00888d8ec0fb-logNode-50f1a038-394b-480f-8f50-84cf776b199e",
			"type": "default",
			"source": "callNode-7d1be4ad-4c7b-4560-b5c6-00888d8ec0fb",
			"target": "logNode-50f1a038-394b-480f-8f50-84cf776b199e",
			"labelBgPadding": [
				8,
				4
			],
			"labelBgBorderRadius": 4,
			"label": "",
			"labelBgStyle": {
				"fill": "#009688",
				"color": "#ffffff",
				"fillOpacity": 0.7
			},
			"labelShowBg": true,
			"sourceHandle": "source_callNode-7d1be4ad-4c7b-4560-b5c6-00888d8ec0fb"
		},
		{
			"id": "logNode-df73659a-2b4d-49ae-b310-11f427795928-whenNode-9d8420e5-ffa7-4dd2-8f27-3540457b3079",
			"type": "default",
			"source": "logNode-df73659a-2b4d-49ae-b310-11f427795928",
			"target": "whenNode-9d8420e5-ffa7-4dd2-8f27-3540457b3079",
			"labelBgPadding": [
				8,
				4
			],
			"labelBgBorderRadius": 4,
			"label": "",
			"labelBgStyle": {
				"fill": "#009688",
				"color": "#ffffff",
				"fillOpacity": 0.7
			},
			"labelShowBg": true,
			"sourceHandle": "source_logNode-df73659a-2b4d-49ae-b310-11f427795928"
		},
		{
			"id": "logNode-50f1a038-394b-480f-8f50-84cf776b199e-whenNode-f9ebdc7e-d721-4918-824f-b38b8038e305",
			"type": "default",
			"source": "logNode-50f1a038-394b-480f-8f50-84cf776b199e",
			"target": "whenNode-f9ebdc7e-d721-4918-824f-b38b8038e305",
			"labelBgPadding": [
				8,
				4
			],
			"labelBgBorderRadius": 4,
			"label": "",
			"labelBgStyle": {
				"fill": "#009688",
				"color": "#ffffff",
				"fillOpacity": 0.7
			},
			"labelShowBg": true,
			"sourceHandle": "source_logNode-50f1a038-394b-480f-8f50-84cf776b199e"
		},
		{
			"id": "whenNode-f9ebdc7e-d721-4918-824f-b38b8038e305-callNode-f1dd0934-98df-44c6-8be3-5004c1f0e2d3",
			"type": "default",
			"source": "whenNode-f9ebdc7e-d721-4918-824f-b38b8038e305",
			"target": "callNode-f1dd0934-98df-44c6-8be3-5004c1f0e2d3",
			"labelBgPadding": [
				8,
				4
			],
			"labelBgBorderRadius": 4,
			"label": "otherwise",
			"labelBgStyle": {
				"fill": "#009688",
				"color": "#ffffff",
				"fillOpacity": 0.7
			},
			"labelShowBg": true,
			"sourceHandle": "source_whenNode-f9ebdc7e-d721-4918-824f-b38b8038e305_otherwise"
		},
		{
			"id": "callNode-f1dd0934-98df-44c6-8be3-5004c1f0e2d3-logNode-1c83b6bc-3cda-4381-941a-5f609d01a12b",
			"type": "default",
			"source": "callNode-f1dd0934-98df-44c6-8be3-5004c1f0e2d3",
			"target": "logNode-1c83b6bc-3cda-4381-941a-5f609d01a12b",
			"labelBgPadding": [
				8,
				4
			],
			"labelBgBorderRadius": 4,
			"label": "",
			"labelBgStyle": {
				"fill": "#009688",
				"color": "#ffffff",
				"fillOpacity": 0.7
			},
			"labelShowBg": true,
			"sourceHandle": "source_callNode-f1dd0934-98df-44c6-8be3-5004c1f0e2d3"
		},
		{
			"id": "logNode-1c83b6bc-3cda-4381-941a-5f609d01a12b-whenNode-5596e065-1f33-42db-a454-cc1f89e59ea2",
			"type": "default",
			"source": "logNode-1c83b6bc-3cda-4381-941a-5f609d01a12b",
			"target": "whenNode-5596e065-1f33-42db-a454-cc1f89e59ea2",
			"labelBgPadding": [
				8,
				4
			],
			"labelBgBorderRadius": 4,
			"label": "",
			"labelBgStyle": {
				"fill": "#009688",
				"color": "#ffffff",
				"fillOpacity": 0.7
			},
			"labelShowBg": true,
			"sourceHandle": "source_logNode-1c83b6bc-3cda-4381-941a-5f609d01a12b"
		},
		{
			"id": "whenNode-5596e065-1f33-42db-a454-cc1f89e59ea2-logNode-40a9057c-7f7b-4ec3-b841-a23ae6394b5f",
			"type": "default",
			"source": "whenNode-5596e065-1f33-42db-a454-cc1f89e59ea2",
			"target": "logNode-40a9057c-7f7b-4ec3-b841-a23ae6394b5f",
			"labelBgPadding": [
				8,
				4
			],
			"labelBgBorderRadius": 4,
			"label": "otherwise",
			"labelBgStyle": {
				"fill": "#009688",
				"color": "#ffffff",
				"fillOpacity": 0.7
			},
			"labelShowBg": true,
			"sourceHandle": "source_whenNode-5596e065-1f33-42db-a454-cc1f89e59ea2_otherwise"
		},
		{
			"id": "logNode-40a9057c-7f7b-4ec3-b841-a23ae6394b5f-assignmentNode-93e25ccb-9795-45db-b492-11eeb627c357",
			"type": "default",
			"source": "logNode-40a9057c-7f7b-4ec3-b841-a23ae6394b5f",
			"target": "assignmentNode-93e25ccb-9795-45db-b492-11eeb627c357",
			"labelBgPadding": [
				8,
				4
			],
			"labelBgBorderRadius": 4,
			"label": "",
			"labelBgStyle": {
				"fill": "#009688",
				"color": "#ffffff",
				"fillOpacity": 0.7
			},
			"labelShowBg": true,
			"sourceHandle": "source_logNode-40a9057c-7f7b-4ec3-b841-a23ae6394b5f"
		},
		{
			"id": "whenNode-5596e065-1f33-42db-a454-cc1f89e59ea2-logNode-3a60855c-7abf-45a9-a26a-34db60545fd7",
			"type": "default",
			"source": "whenNode-5596e065-1f33-42db-a454-cc1f89e59ea2",
			"target": "logNode-3a60855c-7abf-45a9-a26a-34db60545fd7",
			"labelBgPadding": [
				8,
				4
			],
			"labelBgBorderRadius": 4,
			"label": "Condition met",
			"labelBgStyle": {
				"fill": "#009688",
				"color": "#ffffff",
				"fillOpacity": 0.7
			},
			"labelShowBg": true,
			"sourceHandle": "source_whenNode-5596e065-1f33-42db-a454-cc1f89e59ea2_success"
		},
		{
			"id": "logNode-3a60855c-7abf-45a9-a26a-34db60545fd7-finishNode-40609603-e9c5-4c5c-a9c2-f8e88c2922d0",
			"type": "default",
			"source": "logNode-3a60855c-7abf-45a9-a26a-34db60545fd7",
			"target": "finishNode-40609603-e9c5-4c5c-a9c2-f8e88c2922d0",
			"labelBgPadding": [
				8,
				4
			],
			"labelBgBorderRadius": 4,
			"label": "",
			"labelBgStyle": {
				"fill": "#009688",
				"color": "#ffffff",
				"fillOpacity": 0.7
			},
			"labelShowBg": true,
			"sourceHandle": "source_logNode-3a60855c-7abf-45a9-a26a-34db60545fd7"
		},
		{
			"id": "whenNode-f9ebdc7e-d721-4918-824f-b38b8038e305-logNode-f2e8f64e-824e-40a0-acce-a5d19efa7cb3",
			"type": "default",
			"source": "whenNode-f9ebdc7e-d721-4918-824f-b38b8038e305",
			"target": "logNode-f2e8f64e-824e-40a0-acce-a5d19efa7cb3",
			"labelBgPadding": [
				8,
				4
			],
			"labelBgBorderRadius": 4,
			"label": "Condition met",
			"labelBgStyle": {
				"fill": "#009688",
				"color": "#ffffff",
				"fillOpacity": 0.7
			},
			"labelShowBg": true,
			"sourceHandle": "source_whenNode-f9ebdc7e-d721-4918-824f-b38b8038e305_success"
		},
		{
			"id": "logNode-f2e8f64e-824e-40a0-acce-a5d19efa7cb3-assignmentNode-50a70c3d-93ee-4d21-a021-2d41e201b932",
			"type": "default",
			"source": "logNode-f2e8f64e-824e-40a0-acce-a5d19efa7cb3",
			"target": "assignmentNode-50a70c3d-93ee-4d21-a021-2d41e201b932",
			"labelBgPadding": [
				8,
				4
			],
			"labelBgBorderRadius": 4,
			"label": "",
			"labelBgStyle": {
				"fill": "#009688",
				"color": "#ffffff",
				"fillOpacity": 0.7
			},
			"labelShowBg": true,
			"sourceHandle": "source_logNode-f2e8f64e-824e-40a0-acce-a5d19efa7cb3"
		},
		{
			"id": "assignmentNode-50a70c3d-93ee-4d21-a021-2d41e201b932-iterateOverNode-0520ffc9-fed3-4107-af27-830de213457a",
			"type": "default",
			"source": "assignmentNode-50a70c3d-93ee-4d21-a021-2d41e201b932",
			"target": "iterateOverNode-0520ffc9-fed3-4107-af27-830de213457a",
			"labelBgPadding": [
				8,
				4
			],
			"labelBgBorderRadius": 4,
			"label": "",
			"labelBgStyle": {
				"fill": "#009688",
				"color": "#ffffff",
				"fillOpacity": 0.7
			},
			"labelShowBg": true,
			"sourceHandle": "source_assignmentNode-50a70c3d-93ee-4d21-a021-2d41e201b932"
		},
		{
			"source": "rrfNode-e648f293-0be3-49fc-b069-38f1e1ccf4fd",
			"sourceHandle": "source_rrfNode-e648f293-0be3-49fc-b069-38f1e1ccf4fd",
			"target": "whenNode-565629fd-462f-41ea-9569-63364bb79245",
			"targetHandle": "target_whenNode-565629fd-462f-41ea-9569-63364bb79245",
			"label": "",
			"labelBgPadding": [
				8,
				4
			],
			"labelBgBorderRadius": 4,
			"labelBgStyle": {
				"fill": "#009688",
				"color": "#ffffff",
				"fillOpacity": 0.7
			},
			"id": "xy-edge__rrfNode-e648f293-0be3-49fc-b069-38f1e1ccf4fdsource_rrfNode-e648f293-0be3-49fc-b069-38f1e1ccf4fd-whenNode-565629fd-462f-41ea-9569-63364bb79245target_whenNode-565629fd-462f-41ea-9569-63364bb79245"
		}
	],
	"viewport": {
		"x": -2064.6946107116664,
		"y": 237.96072816933847,
		"zoom": 0.8681402276010419
	}
}